pep_tk/VERSION.txt
pep_tk/__init__.py
pep_tk/launch.py
pep_tk/conf/pipeline_manifest.yaml
pep_tk/conf/pipelines/VIAME-JoBBS-Models/dual_stream/JoBBS_seal_yolo_ir_eo_region_trigger.pipe
pep_tk/conf/pipelines/VIAME-JoBBS-Models/models/eo_pb_yolo_tiny_3l.cfg
pep_tk/conf/pipelines/VIAME-JoBBS-Models/models/eo_pb_yolo_tiny_3l.names
pep_tk/conf/pipelines/VIAME-JoBBS-Models/models/eo_pb_yolo_tiny_3l.weights
pep_tk/conf/pipelines/VIAME-JoBBS-Models/models/eo_seals_yolo_tiny_3l_512_1to1bg_nounk.cfg
pep_tk/conf/pipelines/VIAME-JoBBS-Models/models/eo_seals_yolo_tiny_3l_512_1to1bg_nounk.names
pep_tk/conf/pipelines/VIAME-JoBBS-Models/models/eo_seals_yolo_tiny_3l_512_1to1bg_nounk.weights
pep_tk/conf/pipelines/VIAME-JoBBS-Models/models/ir_yolo_tiny_1L64x80.cfg
pep_tk/conf/pipelines/VIAME-JoBBS-Models/models/ir_yolo_tiny_1L64x80.names
pep_tk/conf/pipelines/VIAME-JoBBS-Models/models/ir_yolo_tiny_1L64x80.weights
pep_tk/conf/pipelines/VIAME-JoBBS-Models/single_stream/eo_polarbear_only.pipe
pep_tk/conf/pipelines/VIAME-JoBBS-Models/single_stream/eo_seal_and_polarbear.pipe
pep_tk/conf/pipelines/VIAME-JoBBS-Models/single_stream/eo_seal_only.pipe
pep_tk/conf/pipelines/VIAME-JoBBS-Models/single_stream/ir_hotspot.pipe
pep_tk/core/__init__.py
pep_tk/core/job.py
pep_tk/core/scheduler.py
pep_tk/core/configuration/__init__.py
pep_tk/core/configuration/configurations.py
pep_tk/core/configuration/exceptions.py
pep_tk/core/configuration/pipelines.py
pep_tk/core/configuration/types.py
pep_tk/core/kwiver/__init__.py
pep_tk/core/kwiver/pipeline_compiler.py
pep_tk/core/kwiver/runner.py
pep_tk/core/parser/__init__.py
pep_tk/core/parser/empty_parser.py
pep_tk/core/parser/ini_parser.py
pep_tk/core/parser/load_dataset.py
pep_tk/core/parser/parser.py
pep_tk/core/parser/pd_parser.py
pep_tk/core/utilities/__init__.py
pep_tk/core/utilities/jsonfile.py
pep_tk/lib/img/help.png
pep_tk/lib/img/icon_160x160.png
pep_tk/lib/img/icon_24x24.png
pep_tk/lib/img/icon_80x80.png
pep_tk/lib/img/icons/1x/cancelled.png
pep_tk-1.1.0.dist-info/LICENSE
pep_tk-1.1.0.dist-info/METADATA
pep_tk-1.1.0.dist-info/WHEEL
pep_tk-1.1.0.dist-info/entry_points.txt
pep_tk-1.1.0.dist-info/top_level.txt
pep_tk-1.1.0.dist-info/RECORD
