Metadata-Version: 2.1
Name: pep-tk
Version: 1.1.0
Summary: Polar Ecosystems Program Toolkit
Home-page: https://github.com/readicculus/pep_gui
Author: Yuval Boss
Author-email: yuval@uw.edu
License: UNKNOWN
Platform: UNKNOWN
Requires-Python: >=3.8
License-File: LICENSE
Requires-Dist: PyYAML (==5.4.1)
Requires-Dist: setuptools (~=52.0.0)
Requires-Dist: pandas
Requires-Dist: PySimpleGUI (==4.47.0)
Requires-Dist: dataclasses (==0.8) ; python_version < "3.7"
